mjob/__init__.py
mjob/mjob.py
mjob-1.2.0.dist-info/LICENSE
mjob-1.2.0.dist-info/METADATA
mjob-1.2.0.dist-info/WHEEL
mjob-1.2.0.dist-info/entry_points.txt
mjob-1.2.0.dist-info/top_level.txt
mjob-1.2.0.dist-info/RECORD
