Metadata-Version: 2.1
Name: mjob
Version: 1.2.0
Summary: Perform parallel tasks based on a given file list
Home-page: https://github.com/timekettle/mjob
Author: sirui.li
Author-email: sirui.li@timekettle.co
License: Apache License 2.0
Keywords: multi
Classifier: Development Status :: 5 - Production/Stable
Classifier: License :: OSI Approved :: Apache Software License
Classifier: Operating System :: OS Independent
Classifier: Programming Language :: Python :: 3
Classifier: Programming Language :: Python :: 3.6
Classifier: Programming Language :: Python :: 3.7
Classifier: Programming Language :: Python :: 3.8
Classifier: Programming Language :: Python :: 3.9
License-File: LICENSE
Requires-Dist: tqdm
